{"diary/2026-06-05":{"slug":"diary/2026-06-05","filePath":"diary/2026-06-05.md","title":"2026-06-05","links":[],"tags":[],"content":"今天创建了我的个人网站！"},"index":{"slug":"index","filePath":"index.md","title":"关于本站","links":[],"tags":[],"content":"这里会留下很多没有结论的话。\n有些是日记，\n有些只是凌晨突然出现的念头，\n也有一些情绪化、矛盾、甚至会被未来的我否定的东西。\n我希望！\n这里的内容能永远停留在这里，\n外面的世界太复杂了，\n我怕它们一出去就被淹没在茫茫人海中了。\n现实中的我和这里记录下来的东西，\n未必永远一致。\n但至少在写下它们的那一刻，\n它们都是真实存在过的。"},"diary/index":{"slug":"diary/index","filePath":"diary/index.md","title":"diary","links":[],"tags":[],"content":""},"tags/index":{"slug":"tags/index","filePath":"tags/index.md","title":"Tag Index","links":[],"tags":[],"content":""}}